packmon/__init__.py
packmon/packmon.py
packmon-0.3.1.dist-info/LICENSE
packmon-0.3.1.dist-info/METADATA
packmon-0.3.1.dist-info/WHEEL
packmon-0.3.1.dist-info/entry_points.txt
packmon-0.3.1.dist-info/top_level.txt
packmon-0.3.1.dist-info/RECORD
