Metadata-Version: 2.1
Name: packmon
Version: 0.3.1
Summary: Tool to monitor aging packages in order to detect obsolescence or updates
Home-page: https://framagit.org/Mindiell/packmon
Author: Mindiell
Author-email: mindiell@mindiell.net
License: GNU AFFERO GENERAL PUBLIC LICENSE version 3 or later
Classifier: Development Status :: 4 - Beta
Classifier: Environment :: Console
Classifier: Intended Audience :: Developers
Classifier: License :: OSI Approved :: GNU Affero General Public License v3 or later (AGPLv3+)
Classifier: Operating System :: OS Independent
Classifier: Programming Language :: Python :: 3
Classifier: Programming Language :: Python :: 3.7
Classifier: Programming Language :: Python :: 3.8
Classifier: Programming Language :: Python :: 3.9
Classifier: Programming Language :: Python :: 3.10
Classifier: Topic :: Software Development :: Quality Assurance
Requires-Python: >=3.7
License-File: LICENSE
